{
  "id": "props",
  "imageUrl": "/atlas/props.png",
  "width": 128,
  "height": 512,
  "frames": {
    "decoration/scarecrow": {
      "x": 1,
      "y": 1,
      "w": 16,
      "h": 16
    },
    "decoration/windmill": {
      "x": 18,
      "y": 1,
      "w": 16,
      "h": 16
    },
    "decoration/flower-bed": {
      "x": 35,
      "y": 1,
      "w": 16,
      "h": 16
    },
    "decoration/fence-art": {
      "x": 52,
      "y": 1,
      "w": 16,
      "h": 16
    },
    "decoration/barrel": {
      "x": 69,
      "y": 1,
      "w": 16,
      "h": 16
    },
    "decoration/crate": {
      "x": 86,
      "y": 1,
      "w": 16,
      "h": 16
    },
    "decoration/potted-plant": {
      "x": 103,
      "y": 1,
      "w": 16,
      "h": 16
    },
    "decoration/lamp-post": {
      "x": 1,
      "y": 18,
      "w": 16,
      "h": 16
    },
    "decoration/signpost": {
      "x": 18,
      "y": 18,
      "w": 16,
      "h": 16
    },
    "decoration/hay-bale": {
      "x": 35,
      "y": 18,
      "w": 16,
      "h": 16
    },
    "decoration/bush": {
      "x": 52,
      "y": 18,
      "w": 16,
      "h": 16
    },
    "decoration/log-stack": {
      "x": 69,
      "y": 18,
      "w": 16,
      "h": 16
    },
    "decoration/stone-lantern": {
      "x": 86,
      "y": 18,
      "w": 16,
      "h": 16
    },
    "decoration/torii": {
      "x": 103,
      "y": 18,
      "w": 16,
      "h": 16
    },
    "decoration/buoy": {
      "x": 1,
      "y": 35,
      "w": 16,
      "h": 16
    },
    "decoration/fish-basket": {
      "x": 18,
      "y": 35,
      "w": 16,
      "h": 16
    },
    "decoration/anchor": {
      "x": 35,
      "y": 35,
      "w": 16,
      "h": 16
    },
    "decoration/mushroom-cluster": {
      "x": 52,
      "y": 35,
      "w": 16,
      "h": 16
    },
    "decoration/fern": {
      "x": 69,
      "y": 35,
      "w": 16,
      "h": 16
    },
    "decoration/ore-cart": {
      "x": 86,
      "y": 35,
      "w": 16,
      "h": 16
    },
    "decoration/rubble": {
      "x": 103,
      "y": 35,
      "w": 16,
      "h": 16
    },
    "decoration/grain-sack": {
      "x": 1,
      "y": 52,
      "w": 16,
      "h": 16
    },
    "decoration/flour-bag": {
      "x": 18,
      "y": 52,
      "w": 16,
      "h": 16
    },
    "decoration/cattail": {
      "x": 35,
      "y": 52,
      "w": 16,
      "h": 16
    },
    "decoration/cairn": {
      "x": 52,
      "y": 52,
      "w": 16,
      "h": 16
    },
    "decoration/bird-a": {
      "x": 69,
      "y": 52,
      "w": 16,
      "h": 16
    },
    "decoration/bird-b": {
      "x": 86,
      "y": 52,
      "w": 16,
      "h": 16
    },
    "decoration/leaf-a": {
      "x": 103,
      "y": 52,
      "w": 16,
      "h": 16
    },
    "decoration/leaf-autumn": {
      "x": 1,
      "y": 69,
      "w": 16,
      "h": 16
    },
    "decoration/duck-a": {
      "x": 18,
      "y": 69,
      "w": 16,
      "h": 16
    },
    "decoration/duck-b": {
      "x": 35,
      "y": 69,
      "w": 16,
      "h": 16
    },
    "decoration/whale": {
      "x": 52,
      "y": 69,
      "w": 32,
      "h": 16
    },
    "decoration/volcano": {
      "x": 85,
      "y": 69,
      "w": 32,
      "h": 32
    },
    "decoration/casino": {
      "x": 1,
      "y": 102,
      "w": 32,
      "h": 48
    },
    "decoration/casino-hotel": {
      "x": 34,
      "y": 102,
      "w": 32,
      "h": 32
    },
    "decoration/fish-clown-a": {
      "x": 67,
      "y": 102,
      "w": 16,
      "h": 16
    },
    "decoration/fish-clown-b": {
      "x": 84,
      "y": 102,
      "w": 16,
      "h": 16
    },
    "decoration/fish-blue-a": {
      "x": 101,
      "y": 102,
      "w": 16,
      "h": 16
    },
    "decoration/fish-blue-b": {
      "x": 1,
      "y": 151,
      "w": 16,
      "h": 16
    },
    "decoration/fish-yellow-a": {
      "x": 18,
      "y": 151,
      "w": 16,
      "h": 16
    },
    "decoration/fish-yellow-b": {
      "x": 35,
      "y": 151,
      "w": 16,
      "h": 16
    },
    "decoration/slot-machine": {
      "x": 52,
      "y": 151,
      "w": 16,
      "h": 32
    },
    "decoration/blackjack-table": {
      "x": 69,
      "y": 151,
      "w": 32,
      "h": 24
    },
    "decoration/roulette": {
      "x": 1,
      "y": 184,
      "w": 32,
      "h": 32
    },
    "decoration/shell-game": {
      "x": 34,
      "y": 184,
      "w": 32,
      "h": 24
    },
    "decoration/dice-table": {
      "x": 67,
      "y": 184,
      "w": 32,
      "h": 24
    },
    "decoration/ring-post": {
      "x": 100,
      "y": 184,
      "w": 16,
      "h": 32
    },
    "decoration/ring-ropes": {
      "x": 1,
      "y": 217,
      "w": 32,
      "h": 16
    },
    "decoration/crowd-stand": {
      "x": 34,
      "y": 217,
      "w": 16,
      "h": 16
    },
    "decoration/seabed-starfish": {
      "x": 51,
      "y": 217,
      "w": 16,
      "h": 16
    },
    "decoration/seabed-crab": {
      "x": 68,
      "y": 217,
      "w": 16,
      "h": 16
    },
    "decoration/seabed-sand-dollar": {
      "x": 85,
      "y": 217,
      "w": 16,
      "h": 16
    },
    "decoration/seabed-anemone": {
      "x": 102,
      "y": 217,
      "w": 16,
      "h": 16
    },
    "decoration/kelp-a": {
      "x": 1,
      "y": 234,
      "w": 16,
      "h": 16
    },
    "decoration/kelp-b": {
      "x": 18,
      "y": 234,
      "w": 16,
      "h": 16
    },
    "decoration/jelly-a": {
      "x": 35,
      "y": 234,
      "w": 16,
      "h": 16
    },
    "decoration/jelly-b": {
      "x": 52,
      "y": 234,
      "w": 16,
      "h": 16
    },
    "decoration/turtle-a": {
      "x": 69,
      "y": 234,
      "w": 16,
      "h": 16
    },
    "decoration/turtle-b": {
      "x": 86,
      "y": 234,
      "w": 16,
      "h": 16
    },
    "decoration/fish-green-a": {
      "x": 103,
      "y": 234,
      "w": 16,
      "h": 16
    },
    "decoration/fish-green-b": {
      "x": 1,
      "y": 251,
      "w": 16,
      "h": 16
    }
  },
  "inputsHash": "7e7397c137143af3a245b02e3e34fe65631002fe4190e88e8348ebad054540d9"
}